{
  "results": [
    {
      "span": "00:00:03.5700000",
      "steps": 33,
      "taskName": "AppStart",
      "measurementName": "Page show"
    },
    {
      "span": "00:00:04.3570000",
      "steps": 73,
      "taskName": "AppStart",
      "measurementName": "Page show"
    },
    {
      "span": "00:00:06.0840000",
      "steps": 130,
      "taskName": "AppStart",
      "measurementName": "Page show"
    },
    {
      "span": "00:00:05.6750000",
      "steps": 123,
      "taskName": "AppStart",
      "measurementName": "Page show"
    },
    {
      "span": "00:00:06.0920000",
      "steps": 129,
      "taskName": "AppStart",
      "measurementName": "Page show"
    },
    {
      "span": "00:00:05.9590000",
      "steps": 6,
      "taskName": "AppStart",
      "measurementName": "Reach managed"
    },
    {
      "span": "00:00:05.9740000",
      "steps": 6,
      "taskName": "AppStart",
      "measurementName": "Reach managed"
    },
    {
      "span": "00:00:11.7950000",
      "steps": 5,
      "taskName": "AppStart",
      "measurementName": "Reach managed"
    },
    {
      "span": "00:00:12.8190000",
      "steps": 6,
      "taskName": "AppStart",
      "measurementName": "Reach managed"
    },
    {
      "span": "00:00:09.4580000",
      "steps": 2,
      "taskName": "AppStart",
      "measurementName": "Reach managed"
    },
    {
      "span": "00:00:28.5730000",
      "steps": 3,
      "taskName": "AppStart",
      "measurementName": "Reach managed cold"
    },
    {
      "span": "00:00:21.2650000",
      "steps": 3,
      "taskName": "AppStart",
      "measurementName": "Reach managed cold"
    },
    {
      "span": "00:00:21.2940000",
      "steps": 3,
      "taskName": "AppStart",
      "measurementName": "Reach managed cold"
    },
    {
      "span": "00:00:21.3970000",
      "steps": 3,
      "taskName": "AppStart",
      "measurementName": "Reach managed cold"
    },
    {
      "span": "00:00:21.2040000",
      "steps": 3,
      "taskName": "AppStart",
      "measurementName": "Reach managed cold"
    },
    {
      "span": "00:00:05.8020000",
      "steps": 41,
      "taskName": "AppStart",
      "measurementName": "Blazor Page show"
    },
    {
      "span": "00:00:05.3120000",
      "steps": 38,
      "taskName": "AppStart",
      "measurementName": "Blazor Page show"
    },
    {
      "span": "00:00:05.8270000",
      "steps": 45,
      "taskName": "AppStart",
      "measurementName": "Blazor Page show"
    },
    {
      "span": "00:00:06.1420000",
      "steps": 43,
      "taskName": "AppStart",
      "measurementName": "Blazor Page show"
    },
    {
      "span": "00:00:05.4260000",
      "steps": 40,
      "taskName": "AppStart",
      "measurementName": "Blazor Page show"
    },
    {
      "span": "00:00:05.4200000",
      "steps": 3,
      "taskName": "AppStart",
      "measurementName": "Blazor Reach managed"
    },
    {
      "span": "00:00:05.5280000",
      "steps": 3,
      "taskName": "AppStart",
      "measurementName": "Blazor Reach managed"
    },
    {
      "span": "00:00:08.8020000",
      "steps": 2,
      "taskName": "AppStart",
      "measurementName": "Blazor Reach managed"
    },
    {
      "span": "00:00:09.3790000",
      "steps": 2,
      "taskName": "AppStart",
      "measurementName": "Blazor Reach managed"
    },
    {
      "span": "00:00:07.1710000",
      "steps": 1,
      "taskName": "AppStart",
      "measurementName": "Blazor Reach managed"
    },
    {
      "span": "00:00:17.2770000",
      "steps": 1,
      "taskName": "AppStart",
      "measurementName": "Blazor First UI"
    },
    {
      "span": "00:00:09.5820000",
      "steps": 2,
      "taskName": "AppStart",
      "measurementName": "Blazor First UI"
    },
    {
      "span": "00:00:09.5400000",
      "steps": 2,
      "taskName": "AppStart",
      "measurementName": "Blazor First UI"
    },
    {
      "span": "00:00:08.8170000",
      "steps": 2,
      "taskName": "AppStart",
      "measurementName": "Blazor First UI"
    },
    {
      "span": "00:00:09.1610000",
      "steps": 2,
      "taskName": "AppStart",
      "measurementName": "Blazor First UI"
    },
    {
      "span": "00:00:28.3760000",
      "steps": 3,
      "taskName": "AppStart",
      "measurementName": "Blazor Reach managed cold"
    },
    {
      "span": "00:00:28.4510000",
      "steps": 3,
      "taskName": "AppStart",
      "measurementName": "Blazor Reach managed cold"
    },
    {
      "span": "00:00:28.1380000",
      "steps": 3,
      "taskName": "AppStart",
      "measurementName": "Blazor Reach managed cold"
    },
    {
      "span": "00:00:28.5090000",
      "steps": 3,
      "taskName": "AppStart",
      "measurementName": "Blazor Reach managed cold"
    },
    {
      "span": "00:00:28.4920000",
      "steps": 3,
      "taskName": "AppStart",
      "measurementName": "Blazor Reach managed cold"
    },
    {
      "span": "00:00:05.5970000",
      "steps": 83,
      "taskName": "AppStart",
      "measurementName": "Browser Page show"
    },
    {
      "span": "00:00:05.8410000",
      "steps": 76,
      "taskName": "AppStart",
      "measurementName": "Browser Page show"
    },
    {
      "span": "00:00:06.0700000",
      "steps": 81,
      "taskName": "AppStart",
      "measurementName": "Browser Page show"
    },
    {
      "span": "00:00:05.4310000",
      "steps": 79,
      "taskName": "AppStart",
      "measurementName": "Browser Page show"
    },
    {
      "span": "00:00:05.4370000",
      "steps": 79,
      "taskName": "AppStart",
      "measurementName": "Browser Page show"
    },
    {
      "span": "00:00:09.7070000",
      "steps": 9,
      "taskName": "AppStart",
      "measurementName": "Browser Reach managed"
    },
    {
      "span": "00:00:07.4940000",
      "steps": 3,
      "taskName": "AppStart",
      "measurementName": "Browser Reach managed"
    },
    {
      "span": "00:00:04.9080000",
      "steps": 2,
      "taskName": "AppStart",
      "measurementName": "Browser Reach managed"
    },
    {
      "span": "00:00:07.3550000",
      "steps": 3,
      "taskName": "AppStart",
      "measurementName": "Browser Reach managed"
    },
    {
      "span": "00:00:07.3740000",
      "steps": 3,
      "taskName": "AppStart",
      "measurementName": "Browser Reach managed"
    },
    {
      "span": "00:00:21.2650000",
      "steps": 6,
      "taskName": "AppStart",
      "measurementName": "Browser Reach managed cold"
    },
    {
      "span": "00:00:21.2010000",
      "steps": 6,
      "taskName": "AppStart",
      "measurementName": "Browser Reach managed cold"
    },
    {
      "span": "00:00:21.0990000",
      "steps": 6,
      "taskName": "AppStart",
      "measurementName": "Browser Reach managed cold"
    },
    {
      "span": "00:00:21.0630000",
      "steps": 6,
      "taskName": "AppStart",
      "measurementName": "Browser Reach managed cold"
    },
    {
      "span": "00:00:21.2370000",
      "steps": 6,
      "taskName": "AppStart",
      "measurementName": "Browser Reach managed cold"
    },
    {
      "span": "00:00:00.9490000",
      "steps": 3701274,
      "taskName": "Exceptions",
      "measurementName": "NoExceptionHandling"
    },
    {
      "span": "00:00:00.9550000",
      "steps": 3743317,
      "taskName": "Exceptions",
      "measurementName": "NoExceptionHandling"
    },
    {
      "span": "00:00:00.9610000",
      "steps": 3743317,
      "taskName": "Exceptions",
      "measurementName": "NoExceptionHandling"
    },
    {
      "span": "00:00:00.9760000",
      "steps": 3640571,
      "taskName": "Exceptions",
      "measurementName": "NoExceptionHandling"
    },
    {
      "span": "00:00:00.9770000",
      "steps": 3650498,
      "taskName": "Exceptions",
      "measurementName": "NoExceptionHandling"
    },
    {
      "span": "00:00:01.1620000",
      "steps": 2542741,
      "taskName": "Exceptions",
      "measurementName": "TryCatch"
    },
    {
      "span": "00:00:02.2870000",
      "steps": 5001000,
      "taskName": "Exceptions",
      "measurementName": "TryCatch"
    },
    {
      "span": "00:00:01.1620000",
      "steps": 2542741,
      "taskName": "Exceptions",
      "measurementName": "TryCatch"
    },
    {
      "span": "00:00:01.1620000",
      "steps": 2539372,
      "taskName": "Exceptions",
      "measurementName": "TryCatch"
    },
    {
      "span": "00:00:01.1620000",
      "steps": 2539372,
      "taskName": "Exceptions",
      "measurementName": "TryCatch"
    },
    {
      "span": "00:00:04.0280000",
      "steps": 101000,
      "taskName": "Exceptions",
      "measurementName": "TryCatchThrow"
    },
    {
      "span": "00:00:08.6960000",
      "steps": 235501,
      "taskName": "Exceptions",
      "measurementName": "TryCatchThrow"
    },
    {
      "span": "00:00:04.7730000",
      "steps": 129205,
      "taskName": "Exceptions",
      "measurementName": "TryCatchThrow"
    },
    {
      "span": "00:00:04.8040000",
      "steps": 126000,
      "taskName": "Exceptions",
      "measurementName": "TryCatchThrow"
    },
    {
      "span": "00:00:04.8850000",
      "steps": 132578,
      "taskName": "Exceptions",
      "measurementName": "TryCatchThrow"
    },
    {
      "span": "00:00:05.0860000",
      "steps": 9028571,
      "taskName": "Exceptions",
      "measurementName": "TryCatchFilter"
    },
    {
      "span": "00:00:05.0680000",
      "steps": 9028571,
      "taskName": "Exceptions",
      "measurementName": "TryCatchFilter"
    },
    {
      "span": "00:00:04.9820000",
      "steps": 8871929,
      "taskName": "Exceptions",
      "measurementName": "TryCatchFilter"
    },
    {
      "span": "00:00:05.0710000",
      "steps": 9028571,
      "taskName": "Exceptions",
      "measurementName": "TryCatchFilter"
    },
    {
      "span": "00:00:04.9860000",
      "steps": 8871929,
      "taskName": "Exceptions",
      "measurementName": "TryCatchFilter"
    },
    {
      "span": "00:00:04.9330000",
      "steps": 14805882,
      "taskName": "Exceptions",
      "measurementName": "TryCatchFilterInline"
    },
    {
      "span": "00:00:04.9310000",
      "steps": 14805882,
      "taskName": "Exceptions",
      "measurementName": "TryCatchFilterInline"
    },
    {
      "span": "00:00:04.9320000",
      "steps": 14805882,
      "taskName": "Exceptions",
      "measurementName": "TryCatchFilterInline"
    },
    {
      "span": "00:00:01.6670000",
      "steps": 5001000,
      "taskName": "Exceptions",
      "measurementName": "TryCatchFilterInline"
    },
    {
      "span": "00:00:04.9310000",
      "steps": 14805882,
      "taskName": "Exceptions",
      "measurementName": "TryCatchFilterInline"
    },
    {
      "span": "00:00:02.8110000",
      "steps": 54763,
      "taskName": "Exceptions",
      "measurementName": "TryCatchFilterThrow"
    },
    {
      "span": "00:00:10.2590000",
      "steps": 193879,
      "taskName": "Exceptions",
      "measurementName": "TryCatchFilterThrow"
    },
    {
      "span": "00:00:05.1740000",
      "steps": 99039,
      "taskName": "Exceptions",
      "measurementName": "TryCatchFilterThrow"
    },
    {
      "span": "00:00:10.3710000",
      "steps": 199009,
      "taskName": "Exceptions",
      "measurementName": "TryCatchFilterThrow"
    },
    {
      "span": "00:00:04.9290000",
      "steps": 93592,
      "taskName": "Exceptions",
      "measurementName": "TryCatchFilterThrow"
    },
    {
      "span": "00:00:05.0360000",
      "steps": 120047,
      "taskName": "Exceptions",
      "measurementName": "TryCatchFilterThrowApplies"
    },
    {
      "span": "00:00:09.1940000",
      "steps": 219104,
      "taskName": "Exceptions",
      "measurementName": "TryCatchFilterThrowApplies"
    },
    {
      "span": "00:00:04.9250000",
      "steps": 117279,
      "taskName": "Exceptions",
      "measurementName": "TryCatchFilterThrowApplies"
    },
    {
      "span": "00:00:09.1950000",
      "steps": 219274,
      "taskName": "Exceptions",
      "measurementName": "TryCatchFilterThrowApplies"
    },
    {
      "span": "00:00:04.9000000",
      "steps": 117279,
      "taskName": "Exceptions",
      "measurementName": "TryCatchFilterThrowApplies"
    },
    {
      "span": "00:00:05.0360000",
      "steps": 15251515,
      "taskName": "Exceptions",
      "measurementName": "TryFinally"
    },
    {
      "span": "00:00:05.0370000",
      "steps": 15251515,
      "taskName": "Exceptions",
      "measurementName": "TryFinally"
    },
    {
      "span": "00:00:05.0370000",
      "steps": 15251515,
      "taskName": "Exceptions",
      "measurementName": "TryFinally"
    },
    {
      "span": "00:00:05.0360000",
      "steps": 15251515,
      "taskName": "Exceptions",
      "measurementName": "TryFinally"
    },
    {
      "span": "00:00:05.0230000",
      "steps": 15251515,
      "taskName": "Exceptions",
      "measurementName": "TryFinally"
    },
    {
      "span": "00:00:05.8090000",
      "steps": 5010,
      "taskName": "Json",
      "measurementName": "non-ASCII text serialize"
    },
    {
      "span": "00:00:05.7640000",
      "steps": 5010,
      "taskName": "Json",
      "measurementName": "non-ASCII text serialize"
    },
    {
      "span": "00:00:05.2430000",
      "steps": 4555,
      "taskName": "Json",
      "measurementName": "non-ASCII text serialize"
    },
    {
      "span": "00:00:05.2400000",
      "steps": 4555,
      "taskName": "Json",
      "measurementName": "non-ASCII text serialize"
    },
    {
      "span": "00:00:05.7640000",
      "steps": 5010,
      "taskName": "Json",
      "measurementName": "non-ASCII text serialize"
    },
    {
      "span": "00:00:04.9400000",
      "steps": 2641,
      "taskName": "Json",
      "measurementName": "non-ASCII text deserialize"
    },
    {
      "span": "00:00:05.1880000",
      "steps": 2787,
      "taskName": "Json",
      "measurementName": "non-ASCII text deserialize"
    },
    {
      "span": "00:00:05.1660000",
      "steps": 2787,
      "taskName": "Json",
      "measurementName": "non-ASCII text deserialize"
    },
    {
      "span": "00:00:05.1670000",
      "steps": 2787,
      "taskName": "Json",
      "measurementName": "non-ASCII text deserialize"
    },
    {
      "span": "00:00:05.1650000",
      "steps": 2787,
      "taskName": "Json",
      "measurementName": "non-ASCII text deserialize"
    },
    {
      "span": "00:00:02.6570000",
      "steps": 50010,
      "taskName": "Json",
      "measurementName": "small serialize"
    },
    {
      "span": "00:00:02.6490000",
      "steps": 50010,
      "taskName": "Json",
      "measurementName": "small serialize"
    },
    {
      "span": "00:00:02.6480000",
      "steps": 50010,
      "taskName": "Json",
      "measurementName": "small serialize"
    },
    {
      "span": "00:00:02.6480000",
      "steps": 50010,
      "taskName": "Json",
      "measurementName": "small serialize"
    },
    {
      "span": "00:00:02.6640000",
      "steps": 50010,
      "taskName": "Json",
      "measurementName": "small serialize"
    },
    {
      "span": "00:00:04.3210000",
      "steps": 25010,
      "taskName": "Json",
      "measurementName": "small deserialize"
    },
    {
      "span": "00:00:04.2940000",
      "steps": 25010,
      "taskName": "Json",
      "measurementName": "small deserialize"
    },
    {
      "span": "00:00:04.2890000",
      "steps": 25010,
      "taskName": "Json",
      "measurementName": "small deserialize"
    },
    {
      "span": "00:00:04.2990000",
      "steps": 25010,
      "taskName": "Json",
      "measurementName": "small deserialize"
    },
    {
      "span": "00:00:04.2740000",
      "steps": 25010,
      "taskName": "Json",
      "measurementName": "small deserialize"
    },
    {
      "span": "00:00:05.1480000",
      "steps": 329,
      "taskName": "Json",
      "measurementName": "large serialize"
    },
    {
      "span": "00:00:05.1220000",
      "steps": 329,
      "taskName": "Json",
      "measurementName": "large serialize"
    },
    {
      "span": "00:00:05.1330000",
      "steps": 329,
      "taskName": "Json",
      "measurementName": "large serialize"
    },
    {
      "span": "00:00:05.1270000",
      "steps": 329,
      "taskName": "Json",
      "measurementName": "large serialize"
    },
    {
      "span": "00:00:05.1300000",
      "steps": 329,
      "taskName": "Json",
      "measurementName": "large serialize"
    },
    {
      "span": "00:00:05.3970000",
      "steps": 114,
      "taskName": "Json",
      "measurementName": "large deserialize"
    },
    {
      "span": "00:00:05.3760000",
      "steps": 114,
      "taskName": "Json",
      "measurementName": "large deserialize"
    },
    {
      "span": "00:00:05.3760000",
      "steps": 114,
      "taskName": "Json",
      "measurementName": "large deserialize"
    },
    {
      "span": "00:00:05.3660000",
      "steps": 114,
      "taskName": "Json",
      "measurementName": "large deserialize"
    },
    {
      "span": "00:00:05.3750000",
      "steps": 114,
      "taskName": "Json",
      "measurementName": "large deserialize"
    },
    {
      "span": "00:00:04.4160000",
      "steps": 75030,
      "taskName": "Span",
      "measurementName": "Reverse bytes"
    },
    {
      "span": "00:00:04.3870000",
      "steps": 75030,
      "taskName": "Span",
      "measurementName": "Reverse bytes"
    },
    {
      "span": "00:00:04.3850000",
      "steps": 75030,
      "taskName": "Span",
      "measurementName": "Reverse bytes"
    },
    {
      "span": "00:00:04.3890000",
      "steps": 75030,
      "taskName": "Span",
      "measurementName": "Reverse bytes"
    },
    {
      "span": "00:00:04.3860000",
      "steps": 75030,
      "taskName": "Span",
      "measurementName": "Reverse bytes"
    },
    {
      "span": "00:00:04.1340000",
      "steps": 50030,
      "taskName": "Span",
      "measurementName": "Reverse chars"
    },
    {
      "span": "00:00:04.1310000",
      "steps": 50030,
      "taskName": "Span",
      "measurementName": "Reverse chars"
    },
    {
      "span": "00:00:06.1940000",
      "steps": 75030,
      "taskName": "Span",
      "measurementName": "Reverse chars"
    },
    {
      "span": "00:00:04.1310000",
      "steps": 50030,
      "taskName": "Span",
      "measurementName": "Reverse chars"
    },
    {
      "span": "00:00:04.1310000",
      "steps": 50030,
      "taskName": "Span",
      "measurementName": "Reverse chars"
    },
    {
      "span": "00:00:04.8540000",
      "steps": 5001000,
      "taskName": "Span",
      "measurementName": "IndexOf bytes"
    },
    {
      "span": "00:00:04.8560000",
      "steps": 5001000,
      "taskName": "Span",
      "measurementName": "IndexOf bytes"
    },
    {
      "span": "00:00:04.8550000",
      "steps": 5001000,
      "taskName": "Span",
      "measurementName": "IndexOf bytes"
    },
    {
      "span": "00:00:04.8560000",
      "steps": 5001000,
      "taskName": "Span",
      "measurementName": "IndexOf bytes"
    },
    {
      "span": "00:00:04.8560000",
      "steps": 5001000,
      "taskName": "Span",
      "measurementName": "IndexOf bytes"
    },
    {
      "span": "00:00:04.1390000",
      "steps": 50030,
      "taskName": "Span",
      "measurementName": "IndexOf chars"
    },
    {
      "span": "00:00:04.1340000",
      "steps": 50030,
      "taskName": "Span",
      "measurementName": "IndexOf chars"
    },
    {
      "span": "00:00:04.1330000",
      "steps": 50030,
      "taskName": "Span",
      "measurementName": "IndexOf chars"
    },
    {
      "span": "00:00:06.1990000",
      "steps": 75030,
      "taskName": "Span",
      "measurementName": "IndexOf chars"
    },
    {
      "span": "00:00:06.2000000",
      "steps": 75030,
      "taskName": "Span",
      "measurementName": "IndexOf chars"
    },
    {
      "span": "00:00:00.0950000",
      "steps": 150030,
      "taskName": "Span",
      "measurementName": "IndexOf strings"
    },
    {
      "span": "00:00:00.0940000",
      "steps": 150030,
      "taskName": "Span",
      "measurementName": "IndexOf strings"
    },
    {
      "span": "00:00:00.0950000",
      "steps": 150030,
      "taskName": "Span",
      "measurementName": "IndexOf strings"
    },
    {
      "span": "00:00:00.0950000",
      "steps": 150030,
      "taskName": "Span",
      "measurementName": "IndexOf strings"
    },
    {
      "span": "00:00:00.0950000",
      "steps": 150030,
      "taskName": "Span",
      "measurementName": "IndexOf strings"
    },
    {
      "span": "00:00:05.1410000",
      "steps": 150030,
      "taskName": "Span",
      "measurementName": "SequenceEqual bytes"
    },
    {
      "span": "00:00:05.1400000",
      "steps": 150030,
      "taskName": "Span",
      "measurementName": "SequenceEqual bytes"
    },
    {
      "span": "00:00:02.5700000",
      "steps": 75030,
      "taskName": "Span",
      "measurementName": "SequenceEqual bytes"
    },
    {
      "span": "00:00:05.1390000",
      "steps": 150030,
      "taskName": "Span",
      "measurementName": "SequenceEqual bytes"
    },
    {
      "span": "00:00:05.1380000",
      "steps": 150030,
      "taskName": "Span",
      "measurementName": "SequenceEqual bytes"
    },
    {
      "span": "00:00:05.0780000",
      "steps": 75030,
      "taskName": "Span",
      "measurementName": "SequenceEqual chars"
    },
    {
      "span": "00:00:05.0790000",
      "steps": 75030,
      "taskName": "Span",
      "measurementName": "SequenceEqual chars"
    },
    {
      "span": "00:00:03.5460000",
      "steps": 50030,
      "taskName": "Span",
      "measurementName": "SequenceEqual chars"
    },
    {
      "span": "00:00:05.0800000",
      "steps": 75030,
      "taskName": "Span",
      "measurementName": "SequenceEqual chars"
    },
    {
      "span": "00:00:03.3880000",
      "steps": 50030,
      "taskName": "Span",
      "measurementName": "SequenceEqual chars"
    },
    {
      "span": "00:00:05.1280000",
      "steps": 2708,
      "taskName": "String",
      "measurementName": "Normalize"
    },
    {
      "span": "00:00:05.1660000",
      "steps": 2757,
      "taskName": "String",
      "measurementName": "Normalize"
    },
    {
      "span": "00:00:05.1710000",
      "steps": 2757,
      "taskName": "String",
      "measurementName": "Normalize"
    },
    {
      "span": "00:00:05.2340000",
      "steps": 2807,
      "taskName": "String",
      "measurementName": "Normalize"
    },
    {
      "span": "00:00:05.1710000",
      "steps": 2757,
      "taskName": "String",
      "measurementName": "Normalize"
    },
    {
      "span": "00:00:05.0550000",
      "steps": 21458,
      "taskName": "String",
      "measurementName": "IsNormalized"
    },
    {
      "span": "00:00:04.4250000",
      "steps": 18780,
      "taskName": "String",
      "measurementName": "IsNormalized"
    },
    {
      "span": "00:00:05.0540000",
      "steps": 21458,
      "taskName": "String",
      "measurementName": "IsNormalized"
    },
    {
      "span": "00:00:05.0550000",
      "steps": 21458,
      "taskName": "String",
      "measurementName": "IsNormalized"
    },
    {
      "span": "00:00:05.0540000",
      "steps": 21458,
      "taskName": "String",
      "measurementName": "IsNormalized"
    },
    {
      "span": "00:00:04.3240000",
      "steps": 150030,
      "taskName": "String",
      "measurementName": "Normalize ASCII"
    },
    {
      "span": "00:00:04.3380000",
      "steps": 150030,
      "taskName": "String",
      "measurementName": "Normalize ASCII"
    },
    {
      "span": "00:00:04.3240000",
      "steps": 150030,
      "taskName": "String",
      "measurementName": "Normalize ASCII"
    },
    {
      "span": "00:00:04.3380000",
      "steps": 150030,
      "taskName": "String",
      "measurementName": "Normalize ASCII"
    },
    {
      "span": "00:00:04.3220000",
      "steps": 150030,
      "taskName": "String",
      "measurementName": "Normalize ASCII"
    },
    {
      "span": "00:00:05.4100000",
      "steps": 3977,
      "taskName": "String",
      "measurementName": "TextInfo ToLower"
    },
    {
      "span": "00:00:05.2440000",
      "steps": 3876,
      "taskName": "String",
      "measurementName": "TextInfo ToLower"
    },
    {
      "span": "00:00:05.4910000",
      "steps": 4084,
      "taskName": "String",
      "measurementName": "TextInfo ToLower"
    },
    {
      "span": "00:00:05.4930000",
      "steps": 4084,
      "taskName": "String",
      "measurementName": "TextInfo ToLower"
    },
    {
      "span": "00:00:05.3280000",
      "steps": 3977,
      "taskName": "String",
      "measurementName": "TextInfo ToLower"
    },
    {
      "span": "00:00:05.5050000",
      "steps": 3977,
      "taskName": "String",
      "measurementName": "TextInfo ToUpper"
    },
    {
      "span": "00:00:05.3600000",
      "steps": 3876,
      "taskName": "String",
      "measurementName": "TextInfo ToUpper"
    },
    {
      "span": "00:00:05.5910000",
      "steps": 4084,
      "taskName": "String",
      "measurementName": "TextInfo ToUpper"
    },
    {
      "span": "00:00:05.8390000",
      "steps": 4315,
      "taskName": "String",
      "measurementName": "TextInfo ToUpper"
    },
    {
      "span": "00:00:05.7480000",
      "steps": 4196,
      "taskName": "String",
      "measurementName": "TextInfo ToUpper"
    },
    {
      "span": "00:00:05.2410000",
      "steps": 780,
      "taskName": "String",
      "measurementName": "TextInfo ToTileCase"
    },
    {
      "span": "00:00:05.3270000",
      "steps": 795,
      "taskName": "String",
      "measurementName": "TextInfo ToTileCase"
    },
    {
      "span": "00:00:05.2990000",
      "steps": 783,
      "taskName": "String",
      "measurementName": "TextInfo ToTileCase"
    },
    {
      "span": "00:00:05.2880000",
      "steps": 787,
      "taskName": "String",
      "measurementName": "TextInfo ToTileCase"
    },
    {
      "span": "00:00:05.2830000",
      "steps": 780,
      "taskName": "String",
      "measurementName": "TextInfo ToTileCase"
    },
    {
      "span": "00:00:05.1000000",
      "steps": 13613,
      "taskName": "String",
      "measurementName": "String Compare"
    },
    {
      "span": "00:00:05.1270000",
      "steps": 14805,
      "taskName": "String",
      "measurementName": "String Compare"
    },
    {
      "span": "00:00:04.9470000",
      "steps": 13257,
      "taskName": "String",
      "measurementName": "String Compare"
    },
    {
      "span": "00:00:04.9840000",
      "steps": 14385,
      "taskName": "String",
      "measurementName": "String Compare"
    },
    {
      "span": "00:00:05.0800000",
      "steps": 13613,
      "taskName": "String",
      "measurementName": "String Compare"
    },
    {
      "span": "00:00:05.1290000",
      "steps": 14805,
      "taskName": "String",
      "measurementName": "String Equals"
    },
    {
      "span": "00:00:04.9770000",
      "steps": 14385,
      "taskName": "String",
      "measurementName": "String Equals"
    },
    {
      "span": "00:00:04.9830000",
      "steps": 14385,
      "taskName": "String",
      "measurementName": "String Equals"
    },
    {
      "span": "00:00:04.9780000",
      "steps": 14385,
      "taskName": "String",
      "measurementName": "String Equals"
    },
    {
      "span": "00:00:04.9830000",
      "steps": 14385,
      "taskName": "String",
      "measurementName": "String Equals"
    },
    {
      "span": "00:00:04.9760000",
      "steps": 14385,
      "taskName": "String",
      "measurementName": "CompareInfo Compare"
    },
    {
      "span": "00:00:04.9750000",
      "steps": 14385,
      "taskName": "String",
      "measurementName": "CompareInfo Compare"
    },
    {
      "span": "00:00:04.9750000",
      "steps": 14385,
      "taskName": "String",
      "measurementName": "CompareInfo Compare"
    },
    {
      "span": "00:00:04.9750000",
      "steps": 14385,
      "taskName": "String",
      "measurementName": "CompareInfo Compare"
    },
    {
      "span": "00:00:04.9760000",
      "steps": 14385,
      "taskName": "String",
      "measurementName": "CompareInfo Compare"
    },
    {
      "span": "00:00:05.9840000",
      "steps": 315,
      "taskName": "String",
      "measurementName": "CompareInfo IsPrefix"
    },
    {
      "span": "00:00:05.9340000",
      "steps": 313,
      "taskName": "String",
      "measurementName": "CompareInfo IsPrefix"
    },
    {
      "span": "00:00:05.9770000",
      "steps": 315,
      "taskName": "String",
      "measurementName": "CompareInfo IsPrefix"
    },
    {
      "span": "00:00:05.9730000",
      "steps": 315,
      "taskName": "String",
      "measurementName": "CompareInfo IsPrefix"
    },
    {
      "span": "00:00:05.9710000",
      "steps": 315,
      "taskName": "String",
      "measurementName": "CompareInfo IsPrefix"
    },
    {
      "span": "00:00:05.9940000",
      "steps": 157,
      "taskName": "String",
      "measurementName": "CompareInfo IsSuffix"
    },
    {
      "span": "00:00:05.9830000",
      "steps": 157,
      "taskName": "String",
      "measurementName": "CompareInfo IsSuffix"
    },
    {
      "span": "00:00:05.9450000",
      "steps": 156,
      "taskName": "String",
      "measurementName": "CompareInfo IsSuffix"
    },
    {
      "span": "00:00:05.9850000",
      "steps": 157,
      "taskName": "String",
      "measurementName": "CompareInfo IsSuffix"
    },
    {
      "span": "00:00:05.9490000",
      "steps": 156,
      "taskName": "String",
      "measurementName": "CompareInfo IsSuffix"
    },
    {
      "span": "00:00:05.9660000",
      "steps": 315,
      "taskName": "String",
      "measurementName": "String StartsWith"
    },
    {
      "span": "00:00:05.9650000",
      "steps": 315,
      "taskName": "String",
      "measurementName": "String StartsWith"
    },
    {
      "span": "00:00:05.9660000",
      "steps": 315,
      "taskName": "String",
      "measurementName": "String StartsWith"
    },
    {
      "span": "00:00:05.9260000",
      "steps": 313,
      "taskName": "String",
      "measurementName": "String StartsWith"
    },
    {
      "span": "00:00:05.9680000",
      "steps": 315,
      "taskName": "String",
      "measurementName": "String StartsWith"
    },
    {
      "span": "00:00:05.9260000",
      "steps": 155,
      "taskName": "String",
      "measurementName": "String EndsWith"
    },
    {
      "span": "00:00:05.9240000",
      "steps": 155,
      "taskName": "String",
      "measurementName": "String EndsWith"
    },
    {
      "span": "00:00:05.9640000",
      "steps": 156,
      "taskName": "String",
      "measurementName": "String EndsWith"
    },
    {
      "span": "00:00:05.9650000",
      "steps": 156,
      "taskName": "String",
      "measurementName": "String EndsWith"
    },
    {
      "span": "00:00:05.9280000",
      "steps": 155,
      "taskName": "String",
      "measurementName": "String EndsWith"
    },
    {
      "span": "00:00:05.9590000",
      "steps": 243,
      "taskName": "String",
      "measurementName": "String IndexOf"
    },
    {
      "span": "00:00:05.9730000",
      "steps": 243,
      "taskName": "String",
      "measurementName": "String IndexOf"
    },
    {
      "span": "00:00:05.9890000",
      "steps": 244,
      "taskName": "String",
      "measurementName": "String IndexOf"
    },
    {
      "span": "00:00:05.9860000",
      "steps": 244,
      "taskName": "String",
      "measurementName": "String IndexOf"
    },
    {
      "span": "00:00:05.9930000",
      "steps": 244,
      "taskName": "String",
      "measurementName": "String IndexOf"
    },
    {
      "span": "00:00:05.9540000",
      "steps": 153,
      "taskName": "String",
      "measurementName": "String LastIndexOf"
    },
    {
      "span": "00:00:05.9540000",
      "steps": 153,
      "taskName": "String",
      "measurementName": "String LastIndexOf"
    },
    {
      "span": "00:00:05.9540000",
      "steps": 153,
      "taskName": "String",
      "measurementName": "String LastIndexOf"
    },
    {
      "span": "00:00:05.9550000",
      "steps": 153,
      "taskName": "String",
      "measurementName": "String LastIndexOf"
    },
    {
      "span": "00:00:05.9540000",
      "steps": 153,
      "taskName": "String",
      "measurementName": "String LastIndexOf"
    },
    {
      "span": "00:00:00.5230000",
      "steps": 1662500,
      "taskName": "Vector",
      "measurementName": "Create Vector128"
    },
    {
      "span": "00:00:00.5380000",
      "steps": 1712903,
      "taskName": "Vector",
      "measurementName": "Create Vector128"
    },
    {
      "span": "00:00:00.5370000",
      "steps": 1712903,
      "taskName": "Vector",
      "measurementName": "Create Vector128"
    },
    {
      "span": "00:00:00.5380000",
      "steps": 1712903,
      "taskName": "Vector",
      "measurementName": "Create Vector128"
    },
    {
      "span": "00:00:00.5230000",
      "steps": 1662500,
      "taskName": "Vector",
      "measurementName": "Create Vector128"
    },
    {
      "span": "00:00:00.5340000",
      "steps": 1570588,
      "taskName": "Vector",
      "measurementName": "Pack Vector128 (Constant)"
    },
    {
      "span": "00:00:00.5340000",
      "steps": 1570588,
      "taskName": "Vector",
      "measurementName": "Pack Vector128 (Constant)"
    },
    {
      "span": "00:00:00.5330000",
      "steps": 1570588,
      "taskName": "Vector",
      "measurementName": "Pack Vector128 (Constant)"
    },
    {
      "span": "00:00:00.5330000",
      "steps": 1570588,
      "taskName": "Vector",
      "measurementName": "Pack Vector128 (Constant)"
    },
    {
      "span": "00:00:00.5330000",
      "steps": 1570588,
      "taskName": "Vector",
      "measurementName": "Pack Vector128 (Constant)"
    },
    {
      "span": "00:00:00.5370000",
      "steps": 1570588,
      "taskName": "Vector",
      "measurementName": "Pack Vector128"
    },
    {
      "span": "00:00:00.5360000",
      "steps": 1570588,
      "taskName": "Vector",
      "measurementName": "Pack Vector128"
    },
    {
      "span": "00:00:00.5360000",
      "steps": 1570588,
      "taskName": "Vector",
      "measurementName": "Pack Vector128"
    },
    {
      "span": "00:00:00.5360000",
      "steps": 1570588,
      "taskName": "Vector",
      "measurementName": "Pack Vector128"
    },
    {
      "span": "00:00:00.5360000",
      "steps": 1570588,
      "taskName": "Vector",
      "measurementName": "Pack Vector128"
    },
    {
      "span": "00:00:00.5330000",
      "steps": 1662500,
      "taskName": "Vector",
      "measurementName": "Add 2 Vector128\u0027s"
    },
    {
      "span": "00:00:00.5330000",
      "steps": 1662500,
      "taskName": "Vector",
      "measurementName": "Add 2 Vector128\u0027s"
    },
    {
      "span": "00:00:00.5330000",
      "steps": 1662500,
      "taskName": "Vector",
      "measurementName": "Add 2 Vector128\u0027s"
    },
    {
      "span": "00:00:00.5330000",
      "steps": 1662500,
      "taskName": "Vector",
      "measurementName": "Add 2 Vector128\u0027s"
    },
    {
      "span": "00:00:00.5330000",
      "steps": 1662500,
      "taskName": "Vector",
      "measurementName": "Add 2 Vector128\u0027s"
    },
    {
      "span": "00:00:00.5300000",
      "steps": 1662500,
      "taskName": "Vector",
      "measurementName": "Multiply 2 Vector128\u0027s"
    },
    {
      "span": "00:00:00.5160000",
      "steps": 1615151,
      "taskName": "Vector",
      "measurementName": "Multiply 2 Vector128\u0027s"
    },
    {
      "span": "00:00:00.5300000",
      "steps": 1662500,
      "taskName": "Vector",
      "measurementName": "Multiply 2 Vector128\u0027s"
    },
    {
      "span": "00:00:00.5310000",
      "steps": 1662500,
      "taskName": "Vector",
      "measurementName": "Multiply 2 Vector128\u0027s"
    },
    {
      "span": "00:00:00.5310000",
      "steps": 1662500,
      "taskName": "Vector",
      "measurementName": "Multiply 2 Vector128\u0027s"
    },
    {
      "span": "00:00:00.5310000",
      "steps": 1662500,
      "taskName": "Vector",
      "measurementName": "Dot product int"
    },
    {
      "span": "00:00:00.5310000",
      "steps": 1662500,
      "taskName": "Vector",
      "measurementName": "Dot product int"
    },
    {
      "span": "00:00:00.5310000",
      "steps": 1662500,
      "taskName": "Vector",
      "measurementName": "Dot product int"
    },
    {
      "span": "00:00:00.5300000",
      "steps": 1662500,
      "taskName": "Vector",
      "measurementName": "Dot product int"
    },
    {
      "span": "00:00:00.5300000",
      "steps": 1662500,
      "taskName": "Vector",
      "measurementName": "Dot product int"
    },
    {
      "span": "00:00:00.5250000",
      "steps": 1662500,
      "taskName": "Vector",
      "measurementName": "Dot product ulong"
    },
    {
      "span": "00:00:00.5250000",
      "steps": 1662500,
      "taskName": "Vector",
      "measurementName": "Dot product ulong"
    },
    {
      "span": "00:00:00.5410000",
      "steps": 1712903,
      "taskName": "Vector",
      "measurementName": "Dot product ulong"
    },
    {
      "span": "00:00:00.5250000",
      "steps": 1662500,
      "taskName": "Vector",
      "measurementName": "Dot product ulong"
    },
    {
      "span": "00:00:00.5410000",
      "steps": 1712903,
      "taskName": "Vector",
      "measurementName": "Dot product ulong"
    },
    {
      "span": "00:00:00.5310000",
      "steps": 1662500,
      "taskName": "Vector",
      "measurementName": "Dot product float"
    },
    {
      "span": "00:00:00.5310000",
      "steps": 1662500,
      "taskName": "Vector",
      "measurementName": "Dot product float"
    },
    {
      "span": "00:00:00.5310000",
      "steps": 1662500,
      "taskName": "Vector",
      "measurementName": "Dot product float"
    },
    {
      "span": "00:00:00.5310000",
      "steps": 1662500,
      "taskName": "Vector",
      "measurementName": "Dot product float"
    },
    {
      "span": "00:00:00.5310000",
      "steps": 1662500,
      "taskName": "Vector",
      "measurementName": "Dot product float"
    },
    {
      "span": "00:00:00.5240000",
      "steps": 1662500,
      "taskName": "Vector",
      "measurementName": "Dot product double"
    },
    {
      "span": "00:00:00.5400000",
      "steps": 1712903,
      "taskName": "Vector",
      "measurementName": "Dot product double"
    },
    {
      "span": "00:00:00.5250000",
      "steps": 1662500,
      "taskName": "Vector",
      "measurementName": "Dot product double"
    },
    {
      "span": "00:00:00.5250000",
      "steps": 1662500,
      "taskName": "Vector",
      "measurementName": "Dot product double"
    },
    {
      "span": "00:00:00.5250000",
      "steps": 1662500,
      "taskName": "Vector",
      "measurementName": "Dot product double"
    },
    {
      "span": "00:00:00.5400000",
      "steps": 1662500,
      "taskName": "Vector",
      "measurementName": "Sum sbyte"
    },
    {
      "span": "00:00:00.5250000",
      "steps": 1615151,
      "taskName": "Vector",
      "measurementName": "Sum sbyte"
    },
    {
      "span": "00:00:00.5260000",
      "steps": 1615151,
      "taskName": "Vector",
      "measurementName": "Sum sbyte"
    },
    {
      "span": "00:00:00.5250000",
      "steps": 1615151,
      "taskName": "Vector",
      "measurementName": "Sum sbyte"
    },
    {
      "span": "00:00:00.5260000",
      "steps": 1615151,
      "taskName": "Vector",
      "measurementName": "Sum sbyte"
    },
    {
      "span": "00:00:00.5280000",
      "steps": 1662500,
      "taskName": "Vector",
      "measurementName": "Sum short"
    },
    {
      "span": "00:00:00.5290000",
      "steps": 1662500,
      "taskName": "Vector",
      "measurementName": "Sum short"
    },
    {
      "span": "00:00:00.5280000",
      "steps": 1662500,
      "taskName": "Vector",
      "measurementName": "Sum short"
    },
    {
      "span": "00:00:00.5280000",
      "steps": 1662500,
      "taskName": "Vector",
      "measurementName": "Sum short"
    },
    {
      "span": "00:00:00.5280000",
      "steps": 1662500,
      "taskName": "Vector",
      "measurementName": "Sum short"
    },
    {
      "span": "00:00:00.5370000",
      "steps": 1712903,
      "taskName": "Vector",
      "measurementName": "Sum uint"
    },
    {
      "span": "00:00:00.5380000",
      "steps": 1712903,
      "taskName": "Vector",
      "measurementName": "Sum uint"
    },
    {
      "span": "00:00:00.5230000",
      "steps": 1662500,
      "taskName": "Vector",
      "measurementName": "Sum uint"
    },
    {
      "span": "00:00:00.5370000",
      "steps": 1712903,
      "taskName": "Vector",
      "measurementName": "Sum uint"
    },
    {
      "span": "00:00:00.5220000",
      "steps": 1662500,
      "taskName": "Vector",
      "measurementName": "Sum uint"
    },
    {
      "span": "00:00:00.5170000",
      "steps": 1662500,
      "taskName": "Vector",
      "measurementName": "Sum double"
    },
    {
      "span": "00:00:00.5320000",
      "steps": 1712903,
      "taskName": "Vector",
      "measurementName": "Sum double"
    },
    {
      "span": "00:00:00.5320000",
      "steps": 1712903,
      "taskName": "Vector",
      "measurementName": "Sum double"
    },
    {
      "span": "00:00:00.5320000",
      "steps": 1712903,
      "taskName": "Vector",
      "measurementName": "Sum double"
    },
    {
      "span": "00:00:00.5320000",
      "steps": 1712903,
      "taskName": "Vector",
      "measurementName": "Sum double"
    },
    {
      "span": "00:00:00.5230000",
      "steps": 1615151,
      "taskName": "Vector",
      "measurementName": "Min float"
    },
    {
      "span": "00:00:00.5380000",
      "steps": 1662500,
      "taskName": "Vector",
      "measurementName": "Min float"
    },
    {
      "span": "00:00:00.5380000",
      "steps": 1662500,
      "taskName": "Vector",
      "measurementName": "Min float"
    },
    {
      "span": "00:00:00.5370000",
      "steps": 1662500,
      "taskName": "Vector",
      "measurementName": "Min float"
    },
    {
      "span": "00:00:00.5230000",
      "steps": 1615151,
      "taskName": "Vector",
      "measurementName": "Min float"
    },
    {
      "span": "00:00:00.5380000",
      "steps": 1662500,
      "taskName": "Vector",
      "measurementName": "Max float"
    },
    {
      "span": "00:00:00.5240000",
      "steps": 1615151,
      "taskName": "Vector",
      "measurementName": "Max float"
    },
    {
      "span": "00:00:00.5380000",
      "steps": 1662500,
      "taskName": "Vector",
      "measurementName": "Max float"
    },
    {
      "span": "00:00:00.5230000",
      "steps": 1615151,
      "taskName": "Vector",
      "measurementName": "Max float"
    },
    {
      "span": "00:00:00.5390000",
      "steps": 1662500,
      "taskName": "Vector",
      "measurementName": "Max float"
    },
    {
      "span": "00:00:00.5410000",
      "steps": 1570588,
      "taskName": "Vector",
      "measurementName": "Min double"
    },
    {
      "span": "00:00:00.5400000",
      "steps": 1570588,
      "taskName": "Vector",
      "measurementName": "Min double"
    },
    {
      "span": "00:00:00.5400000",
      "steps": 1570588,
      "taskName": "Vector",
      "measurementName": "Min double"
    },
    {
      "span": "00:00:00.5420000",
      "steps": 1570588,
      "taskName": "Vector",
      "measurementName": "Min double"
    },
    {
      "span": "00:00:00.5270000",
      "steps": 1528571,
      "taskName": "Vector",
      "measurementName": "Min double"
    },
    {
      "span": "00:00:00.5330000",
      "steps": 1662500,
      "taskName": "Vector",
      "measurementName": "Max double"
    },
    {
      "span": "00:00:00.5320000",
      "steps": 1662500,
      "taskName": "Vector",
      "measurementName": "Max double"
    },
    {
      "span": "00:00:00.5330000",
      "steps": 1662500,
      "taskName": "Vector",
      "measurementName": "Max double"
    },
    {
      "span": "00:00:00.5480000",
      "steps": 1712903,
      "taskName": "Vector",
      "measurementName": "Max double"
    },
    {
      "span": "00:00:00.5330000",
      "steps": 1662500,
      "taskName": "Vector",
      "measurementName": "Max double"
    },
    {
      "span": "00:00:00.5420000",
      "steps": 1488888,
      "taskName": "Vector",
      "measurementName": "Normalize float"
    },
    {
      "span": "00:00:00.5420000",
      "steps": 1488888,
      "taskName": "Vector",
      "measurementName": "Normalize float"
    },
    {
      "span": "00:00:00.5420000",
      "steps": 1488888,
      "taskName": "Vector",
      "measurementName": "Normalize float"
    },
    {
      "span": "00:00:00.5410000",
      "steps": 1488888,
      "taskName": "Vector",
      "measurementName": "Normalize float"
    },
    {
      "span": "00:00:00.5290000",
      "steps": 1451351,
      "taskName": "Vector",
      "measurementName": "Normalize float"
    },
    {
      "span": "00:00:00.5310000",
      "steps": 1528571,
      "taskName": "Vector",
      "measurementName": "Equals Int32"
    },
    {
      "span": "00:00:00.5310000",
      "steps": 1528571,
      "taskName": "Vector",
      "measurementName": "Equals Int32"
    },
    {
      "span": "00:00:00.5310000",
      "steps": 1528571,
      "taskName": "Vector",
      "measurementName": "Equals Int32"
    },
    {
      "span": "00:00:00.1740000",
      "steps": 501000,
      "taskName": "Vector",
      "measurementName": "Equals Int32"
    },
    {
      "span": "00:00:00.5300000",
      "steps": 1528571,
      "taskName": "Vector",
      "measurementName": "Equals Int32"
    },
    {
      "span": "00:00:00.5330000",
      "steps": 1528571,
      "taskName": "Vector",
      "measurementName": "Equals Float"
    },
    {
      "span": "00:00:00.5330000",
      "steps": 1528571,
      "taskName": "Vector",
      "measurementName": "Equals Float"
    },
    {
      "span": "00:00:00.5320000",
      "steps": 1528571,
      "taskName": "Vector",
      "measurementName": "Equals Float"
    },
    {
      "span": "00:00:00.5200000",
      "steps": 1488888,
      "taskName": "Vector",
      "measurementName": "Equals Float"
    },
    {
      "span": "00:00:00.5320000",
      "steps": 1528571,
      "taskName": "Vector",
      "measurementName": "Equals Float"
    },
    {
      "span": "00:00:05.1190000",
      "steps": 289,
      "taskName": "JSInterop",
      "measurementName": "JSExportInt"
    },
    {
      "span": "00:00:05.1440000",
      "steps": 286,
      "taskName": "JSInterop",
      "measurementName": "JSExportInt"
    },
    {
      "span": "00:00:05.1980000",
      "steps": 289,
      "taskName": "JSInterop",
      "measurementName": "JSExportInt"
    },
    {
      "span": "00:00:05.1590000",
      "steps": 287,
      "taskName": "JSInterop",
      "measurementName": "JSExportInt"
    },
    {
      "span": "00:00:05.1070000",
      "steps": 284,
      "taskName": "JSInterop",
      "measurementName": "JSExportInt"
    },
    {
      "span": "00:00:05.3430000",
      "steps": 45,
      "taskName": "JSInterop",
      "measurementName": "JSExportString"
    },
    {
      "span": "00:00:05.3500000",
      "steps": 45,
      "taskName": "JSInterop",
      "measurementName": "JSExportString"
    },
    {
      "span": "00:00:05.3340000",
      "steps": 45,
      "taskName": "JSInterop",
      "measurementName": "JSExportString"
    },
    {
      "span": "00:00:05.3280000",
      "steps": 45,
      "taskName": "JSInterop",
      "measurementName": "JSExportString"
    },
    {
      "span": "00:00:05.3450000",
      "steps": 45,
      "taskName": "JSInterop",
      "measurementName": "JSExportString"
    },
    {
      "span": "00:00:04.9180000",
      "steps": 1260,
      "taskName": "JSInterop",
      "measurementName": "JSImportInt"
    },
    {
      "span": "00:00:05.0550000",
      "steps": 1292,
      "taskName": "JSInterop",
      "measurementName": "JSImportInt"
    },
    {
      "span": "00:00:05.0430000",
      "steps": 1292,
      "taskName": "JSInterop",
      "measurementName": "JSImportInt"
    },
    {
      "span": "00:00:04.8750000",
      "steps": 1260,
      "taskName": "JSInterop",
      "measurementName": "JSImportInt"
    },
    {
      "span": "00:00:05.0450000",
      "steps": 1292,
      "taskName": "JSInterop",
      "measurementName": "JSImportInt"
    },
    {
      "span": "00:00:05.7030000",
      "steps": 63,
      "taskName": "JSInterop",
      "measurementName": "JSImportString"
    },
    {
      "span": "00:00:05.2560000",
      "steps": 66,
      "taskName": "JSInterop",
      "measurementName": "JSImportString"
    },
    {
      "span": "00:00:05.2340000",
      "steps": 66,
      "taskName": "JSInterop",
      "measurementName": "JSImportString"
    },
    {
      "span": "00:00:05.2260000",
      "steps": 66,
      "taskName": "JSInterop",
      "measurementName": "JSImportString"
    },
    {
      "span": "00:00:05.1990000",
      "steps": 66,
      "taskName": "JSInterop",
      "measurementName": "JSImportString"
    },
    {
      "span": "00:00:05.4120000",
      "steps": 36,
      "taskName": "JSInterop",
      "measurementName": "JSImportManyArgs"
    },
    {
      "span": "00:00:05.3940000",
      "steps": 36,
      "taskName": "JSInterop",
      "measurementName": "JSImportManyArgs"
    },
    {
      "span": "00:00:05.3990000",
      "steps": 36,
      "taskName": "JSInterop",
      "measurementName": "JSImportManyArgs"
    },
    {
      "span": "00:00:05.3960000",
      "steps": 36,
      "taskName": "JSInterop",
      "measurementName": "JSImportManyArgs"
    },
    {
      "span": "00:00:05.3910000",
      "steps": 36,
      "taskName": "JSInterop",
      "measurementName": "JSImportManyArgs"
    },
    {
      "span": "00:00:05.8390000",
      "steps": 2,
      "taskName": "JSInterop",
      "measurementName": "JSImportTask"
    },
    {
      "span": "00:00:05.6300000",
      "steps": 2,
      "taskName": "JSInterop",
      "measurementName": "JSImportTask"
    },
    {
      "span": "00:00:05.8130000",
      "steps": 2,
      "taskName": "JSInterop",
      "measurementName": "JSImportTask"
    },
    {
      "span": "00:00:06.0140000",
      "steps": 2,
      "taskName": "JSInterop",
      "measurementName": "JSImportTask"
    },
    {
      "span": "00:00:05.9130000",
      "steps": 2,
      "taskName": "JSInterop",
      "measurementName": "JSImportTask"
    },
    {
      "span": "00:00:08.7770000",
      "steps": 1,
      "taskName": "JSInterop",
      "measurementName": "JSImportTaskFail"
    },
    {
      "span": "00:00:09.3250000",
      "steps": 1,
      "taskName": "JSInterop",
      "measurementName": "JSImportTaskFail"
    },
    {
      "span": "00:00:08.8110000",
      "steps": 1,
      "taskName": "JSInterop",
      "measurementName": "JSImportTaskFail"
    },
    {
      "span": "00:00:09.3890000",
      "steps": 1,
      "taskName": "JSInterop",
      "measurementName": "JSImportTaskFail"
    },
    {
      "span": "00:00:09.3190000",
      "steps": 1,
      "taskName": "JSInterop",
      "measurementName": "JSImportTaskFail"
    },
    {
      "span": "00:00:05.6460000",
      "steps": 5,
      "taskName": "JSInterop",
      "measurementName": "JSImportFail"
    },
    {
      "span": "00:00:05.4970000",
      "steps": 5,
      "taskName": "JSInterop",
      "measurementName": "JSImportFail"
    },
    {
      "span": "00:00:05.4920000",
      "steps": 5,
      "taskName": "JSInterop",
      "measurementName": "JSImportFail"
    },
    {
      "span": "00:00:05.5100000",
      "steps": 5,
      "taskName": "JSInterop",
      "measurementName": "JSImportFail"
    },
    {
      "span": "00:00:05.5150000",
      "steps": 5,
      "taskName": "JSInterop",
      "measurementName": "JSImportFail"
    },
    {
      "span": "00:00:06.4600000",
      "steps": 251000,
      "taskName": "WebSocket",
      "measurementName": "PartialSend_1B"
    },
    {
      "span": "00:00:06.4860000",
      "steps": 251000,
      "taskName": "WebSocket",
      "measurementName": "PartialSend_1B"
    },
    {
      "span": "00:00:06.5100000",
      "steps": 251000,
      "taskName": "WebSocket",
      "measurementName": "PartialSend_1B"
    },
    {
      "span": "00:00:06.4930000",
      "steps": 251000,
      "taskName": "WebSocket",
      "measurementName": "PartialSend_1B"
    },
    {
      "span": "00:00:06.4760000",
      "steps": 251000,
      "taskName": "WebSocket",
      "measurementName": "PartialSend_1B"
    },
    {
      "span": "00:00:00.6550000",
      "steps": 4000,
      "taskName": "WebSocket",
      "measurementName": "PartialSend_64KB"
    },
    {
      "span": "00:00:00.5770000",
      "steps": 4000,
      "taskName": "WebSocket",
      "measurementName": "PartialSend_64KB"
    },
    {
      "span": "00:00:00.6720000",
      "steps": 4000,
      "taskName": "WebSocket",
      "measurementName": "PartialSend_64KB"
    },
    {
      "span": "00:00:00.6400000",
      "steps": 4000,
      "taskName": "WebSocket",
      "measurementName": "PartialSend_64KB"
    },
    {
      "span": "00:00:00.6350000",
      "steps": 4000,
      "taskName": "WebSocket",
      "measurementName": "PartialSend_64KB"
    },
    {
      "span": "00:00:00.2690000",
      "steps": 110,
      "taskName": "WebSocket",
      "measurementName": "PartialSend_1MB"
    },
    {
      "span": "00:00:00.2170000",
      "steps": 110,
      "taskName": "WebSocket",
      "measurementName": "PartialSend_1MB"
    },
    {
      "span": "00:00:00.2010000",
      "steps": 110,
      "taskName": "WebSocket",
      "measurementName": "PartialSend_1MB"
    },
    {
      "span": "00:00:00.1960000",
      "steps": 110,
      "taskName": "WebSocket",
      "measurementName": "PartialSend_1MB"
    },
    {
      "span": "00:00:00.2010000",
      "steps": 110,
      "taskName": "WebSocket",
      "measurementName": "PartialSend_1MB"
    },
    {
      "span": "00:00:03.4590000",
      "steps": 129900,
      "taskName": "WebSocket",
      "measurementName": "PartialReceive_1B"
    },
    {
      "span": "00:00:03.4550000",
      "steps": 129900,
      "taskName": "WebSocket",
      "measurementName": "PartialReceive_1B"
    },
    {
      "span": "00:00:03.4600000",
      "steps": 129900,
      "taskName": "WebSocket",
      "measurementName": "PartialReceive_1B"
    },
    {
      "span": "00:00:03.4470000",
      "steps": 129900,
      "taskName": "WebSocket",
      "measurementName": "PartialReceive_1B"
    },
    {
      "span": "00:00:03.4270000",
      "steps": 129900,
      "taskName": "WebSocket",
      "measurementName": "PartialReceive_1B"
    },
    {
      "span": "00:00:00.0320000",
      "steps": 501,
      "taskName": "WebSocket",
      "measurementName": "PartialReceive_10KB"
    },
    {
      "span": "00:00:00.0160000",
      "steps": 501,
      "taskName": "WebSocket",
      "measurementName": "PartialReceive_10KB"
    },
    {
      "span": "00:00:00.0160000",
      "steps": 501,
      "taskName": "WebSocket",
      "measurementName": "PartialReceive_10KB"
    },
    {
      "span": "00:00:00.0150000",
      "steps": 501,
      "taskName": "WebSocket",
      "measurementName": "PartialReceive_10KB"
    },
    {
      "span": "00:00:00.0190000",
      "steps": 501,
      "taskName": "WebSocket",
      "measurementName": "PartialReceive_10KB"
    },
    {
      "span": "00:00:00.0040000",
      "steps": 100,
      "taskName": "WebSocket",
      "measurementName": "PartialReceive_100KB"
    },
    {
      "span": "00:00:00.0060000",
      "steps": 100,
      "taskName": "WebSocket",
      "measurementName": "PartialReceive_100KB"
    },
    {
      "span": "00:00:00.0030000",
      "steps": 100,
      "taskName": "WebSocket",
      "measurementName": "PartialReceive_100KB"
    },
    {
      "span": "00:00:00.0020000",
      "steps": 100,
      "taskName": "WebSocket",
      "measurementName": "PartialReceive_100KB"
    },
    {
      "span": "00:00:00.0030000",
      "steps": 100,
      "taskName": "WebSocket",
      "measurementName": "PartialReceive_100KB"
    }
  ],
  "minTimes": {
    "AppStart, Page show": 46.13821138211382,
    "AppStart, Reach managed": 993.1666666666666,
    "AppStart, Reach managed cold": 7068,
    "AppStart, Blazor Page show": 129.48888888888888,
    "AppStart, Blazor Reach managed": 1806.6666666666667,
    "AppStart, Blazor First UI": 4408.5,
    "AppStart, Blazor Reach managed cold": 9379.333333333334,
    "AppStart, Browser Page show": 67.43373493975903,
    "AppStart, Browser Reach managed": 1078.5555555555557,
    "AppStart, Browser Reach managed cold": 3510.5,
    "Exceptions, NoExceptionHandling": 0.00025512132688735684,
    "Exceptions, TryCatch": 0.0004569871646384748,
    "Exceptions, TryCatchThrow": 0.03684623391512921,
    "Exceptions, TryCatchFilter": 0.0005613291405694212,
    "Exceptions, TryCatchFilterInline": 0.0003330433134615013,
    "Exceptions, TryCatchFilterThrow": 0.05133027774227124,
    "Exceptions, TryCatchFilterThrowApplies": 0.04178071095422028,
    "Exceptions, TryFinally": 0.0003293443307107523,
    "Json, non-ASCII text serialize": 1.150384193194292,
    "Json, non-ASCII text deserialize": 1.8532472192321492,
    "Json, small serialize": 0.0529494101179764,
    "Json, small deserialize": 0.17089164334266294,
    "Json, large serialize": 15.56838905775076,
    "Json, large deserialize": 47.07017543859649,
    "Span, Reverse bytes": 0.0584432893509263,
    "Span, Reverse chars": 0.08255364520858323,
    "Span, IndexOf bytes": 0.0009706058788242351,
    "Span, IndexOf chars": 0.08261043373975614,
    "Span, IndexOf strings": 0.0006265413583949877,
    "Span, SequenceEqual bytes": 0.034246484036526026,
    "Span, SequenceEqual chars": 0.06767959482873517,
    "String, Normalize": 1.8646241539009618,
    "String, IsNormalized": 0.23552987230869607,
    "String, Normalize ASCII": 0.02880757181896954,
    "String, TextInfo ToLower": 1.3397032939401559,
    "String, TextInfo ToUpper": 1.353186558516802,
    "String, TextInfo ToTileCase": 6.70062893081761,
    "String, String Compare": 0.3463019250253293,
    "String, String Equals": 0.345985401459854,
    "String, CompareInfo Compare": 0.345846367744178,
    "String, CompareInfo IsPrefix": 18.955555555555556,
    "String, CompareInfo IsSuffix": 38.10828025477707,
    "String, String StartsWith": 18.93290734824281,
    "String, String EndsWith": 38.21935483870968,
    "String, String IndexOf": 24.522633744855966,
    "String, String LastIndexOf": 38.91503267973856,
    "Vector, Create Vector128": 0.0003135028661868185,
    "Vector, Pack Vector128 (Constant)": 0.00033936334672110064,
    "Vector, Pack Vector128": 0.0003412734593668104,
    "Vector, Add 2 Vector128\u0027s": 0.0003206015037593985,
    "Vector, Multiply 2 Vector128\u0027s": 0.000318796992481203,
    "Vector, Dot product int": 0.000318796992481203,
    "Vector, Dot product ulong": 0.00031578947368421053,
    "Vector, Dot product float": 0.0003193984962406015,
    "Vector, Dot product double": 0.00031518796992481205,
    "Vector, Sum sbyte": 0.00032481203007518795,
    "Vector, Sum short": 0.00031759398496240604,
    "Vector, Sum uint": 0.0003135028661868185,
    "Vector, Sum double": 0.0003105838450863826,
    "Vector, Min float": 0.0003230075187969925,
    "Vector, Max float": 0.000323609022556391,
    "Vector, Min double": 0.00034382027622775676,
    "Vector, Max double": 0.00031992471260777755,
    "Vector, Normalize float": 0.00036335842588562737,
    "Vector, Equals Int32": 0.00034672906917637453,
    "Vector, Equals Float": 0.0003480374807581722,
    "JSInterop, JSExportInt": 17.71280276816609,
    "JSInterop, JSExportString": 118.4,
    "JSInterop, JSImportInt": 3.869047619047619,
    "JSInterop, JSImportString": 78.77272727272727,
    "JSInterop, JSImportManyArgs": 149.75,
    "JSInterop, JSImportTask": 2815,
    "JSInterop, JSImportTaskFail": 8777,
    "JSInterop, JSImportFail": 1098.4,
    "WebSocket, PartialSend_1B": 0.025737051792828685,
    "WebSocket, PartialSend_64KB": 0.14425,
    "WebSocket, PartialSend_1MB": 1.7818181818181817,
    "WebSocket, PartialReceive_1B": 0.02638183217859892,
    "WebSocket, PartialReceive_10KB": 0.029940119760479042,
    "WebSocket, PartialReceive_100KB": 0.02
  },
  "timeStamp": "2024-02-15T23:04:35.476Z"
}